<?xml version='1.0' encoding='utf-8'?>
<!DOCTYPE rfc [
  <!ENTITY nbsp    "&#160;">
  <!ENTITY zwsp   "&#8203;">
  <!ENTITY nbhy   "&#8209;">
  <!ENTITY wj     "&#8288;">
]>
<?xml-stylesheet type="text/xsl" href="rfc2629.xslt" ?>
<!-- generated by https://github.com/cabo/kramdown-rfc version 1.6.17 (Ruby 2.7.0) -->
<rfc xmlns:xi="http://www.w3.org/2001/XInclude" ipr="trust200902" docName="draft-ietf-ccamp-if-ref-topo-yang-latest" category="std" consensus="true" tocInclude="true" sortRefs="true" symRefs="true" version="3">
  <!-- xml2rfc v2v3 conversion 3.15.3 -->
  <front>
    <title abbrev="Interface Reference Topology YANG Model">A YANG Data Model for Interface Reference Topology</title>
    <seriesInfo name="Internet-Draft" value="draft-ietf-ccamp-if-ref-topo-yang-latest"/>
    <author initials="J." surname="Ahlberg" fullname="Jonas Ahlberg">
      <organization>Ericsson</organization>
      <address>
        <email>jonas.ahlberg@ericsson.com</email>
      </address>
    </author>
    <author initials="S." surname="Mansfield" fullname="Scott Mansfield">
      <organization>Ericsson</organization>
      <address>
        <email>scott.mansfield@ericsson.com</email>
      </address>
    </author>
    <author initials="M." surname="Ye" fullname="Min Ye">
      <organization>Huawei Technologies</organization>
      <address>
        <email>amy.yemin@huawei.com</email>
      </address>
    </author>
    <author initials="I." surname="Busi" fullname="Italo Busi">
      <organization>Huawei Technologies</organization>
      <address>
        <email>italo.busi@huawei.com</email>
      </address>
    </author>
    <author initials="X." surname="Li" fullname="Xi Li">
      <organization>NEC Laboratories Europe</organization>
      <address>
        <email>xi.li@neclab.eu</email>
      </address>
    </author>
    <author initials="D." surname="Spreafico" fullname="Daniela Spreafico">
      <organization>Nokia - IT</organization>
      <address>
        <email>daniela.spreafico@nokia.com</email>
      </address>
    </author>
    <date year="2023" month="January" day="19"/>
    <area>Routing</area>
    <workgroup>ccamp</workgroup>
    <keyword>Internet-Draft</keyword>
    <abstract>
      <t>This document defines a YANG data model to provide a reference from a termination point in a topology model to interface management information.</t>
    </abstract>
    <note removeInRFC="true">
      <name>Discussion Venues</name>
      <t>Source for this draft and an issue tracker can be found at
    <eref target="https://github.com/ietf-ccamp-wg/draft-ietf-ccamp-mw-topo-yang"/>.</t>
    </note>
  </front>
  <middle>
    <section anchor="introduction">
      <name>Introduction</name>
      <t>This document defines a YANG data model to provide a reference from a termination point in a topology model to interface management information.  It introduces a way to reference the information in a YANG data model for interface management <xref target="RFC8343"/> that could be useful for all types of termination points.  The model augments "YANG Data Model for Traffic Engineering (TE) Topologies" defined in <xref target="RFC8795"/>, which is based on "A YANG Data Model for Network Topologies" defined in <xref target="RFC8345"/>.</t>
      <t>The interface reference model is expected to be used between a Provisioning Network Controller (PNC) and a Multi Domain Service Coordinator(MDSC) <xref target="RFC8453"/>.  Different use cases require access to different attributes and in order not to restrict what use cases can be supported, all attributes supported by the interface management model is with this model made accessible from the topology model.</t>
      <section anchor="terminology-and-definitions">
        <name>Terminology and Definitions</name>
        <t>The following acronyms are used in this document:</t>
        <t>PNC Provisioning Network Controller</t>
        <t>MDSC Multi Domain Service Coordinator</t>
      </section>
      <section anchor="tree-structure">
        <name>Tree Structure</name>
        <t>A simplified graphical representation of the data model is used in chapter 3.1 of this document.  The meaning of the symbols in these diagrams is defined in <xref target="RFC8340"/>.</t>
      </section>
    </section>
    <section anchor="requirements-language">
      <name>Requirements Language</name>
      <t>The key words "MUST", "MUST NOT", "REQUIRED", "SHALL", "SHALL NOT", "SHOULD", "SHOULD NOT", "RECOMMENDED", "NOT RECOMMENDED", "MAY", and "OPTIONAL" in this document are to be interpreted as described in BCP 14 <xref target="RFC2119"/> <xref target="RFC8174"/> when, and only when, they appear in all capitals, as shown here.</t>
    </section>
    <section anchor="termination-point-to-interface-reference-yang-data-model">
      <name>Termination Point to Interface Reference YANG Data Model</name>
      <section anchor="yang-tree">
        <name>YANG Tree</name>
        <sourcecode type="yangtree" name="if.tree"><![CDATA[
module: ietf-tp-interface-reference-topology

augment /nw:networks/nw:network/nw:node/nt:termination-point/tet:te:
  +--rw tp-to-interface-path?   -> /if:interfaces/interface/name
]]></sourcecode>
      </section>
      <section anchor="termination-point-to-interface-reference-yang-data-module">
        <name>Termination Point to Interface Reference YANG Data Module</name>
        <sourcecode type="yang" markers="true" name="ietf-tp-interface-reference-topology.yang"><![CDATA[
module ietf-tp-interface-reference-topology {
  yang-version "1.1";
   namespace
  "urn:ietf:params:xml:ns:yang:ietf-tp-interface-reference-topology";

   prefix "ifref";

   import ietf-network {
     prefix "nw";
     reference "RFC 8345: A YANG Data Model for Network Topologies";
   }

   import ietf-network-topology {
     prefix "nt";
     reference "RFC 8345: A YANG Data Model for Network Topologies";
   }

   import ietf-te-topology {
     prefix "tet";
     reference "RFC 8795: YANG Data Model for Traffic Engineering
                (TE) Topologies";
   }

   import ietf-interfaces {
     prefix if;
     reference
       "RFC 8343";
   }

   organization
     "Internet Engineering Task Force (IETF) CCAMP WG";
   contact
     "WG List: <mailto:ccamp@ietf.org>

//[JonasA] Who would like to be on the list of editors/contributors?
      Editor: Jonas Ahlberg
              <mailto:jonas.ahlberg@ericsson.com>
      Editor: Scott Mansfield
              <mailto:scott.mansfield@ericsson.com>
      Editor: Min Ye
              <mailto:amy.yemin@huawei.com>
      Editor: Italo Busi
              <mailto:Italo.Busi@huawei.com>
      Editor: Xi Li
              <mailto:Xi.Li@neclab.eu>
      Editor: Daniela Spreafico

              <mailto:daniela.spreafico@nokia.com>
     ";

   // Note to RFC Editor: replace XXXX with actual RFC number and
   // remove this note.
   description
     "This is a module for defining a reference from a termination
      point in a te topology to a list element in interfaces
      as defined in RFC 8343.

      Copyright (c) 2020 IETF Trust and the persons identified as
      authors of the code.  All rights reserved.
      Redistribution and use in source and binary forms, with or
      without modification, is permitted pursuant to, and subject to
      the license terms contained in, the Simplified BSD License set
      forth in Section 4.c of the IETF Trust's Legal Provisions
      Relating to IETF Documents
      (http://trustee.ietf.org/license-info).
      This version of this YANG module is part of RFC XXXX
      (https://tools.ietf.org/html/rfcXXXX); see the RFC itself for
      full legal notices.";

   revision 2021-10-20 {
     description
     "First rough draft.";
     reference "";
   }

   /*
    * Groupings
    */
   grouping tp-to-interface-ref {

     description
       "Grouping used for reference between a termination point and
        an interface.";
     leaf tp-to-interface-path {
       type leafref {
         path '/if:interfaces/if:interface/if:name';
       }
       description
         "Leafref expression referencing a list element, identified
          by its name, in interfaces as defined in RFC 8343.";
     }
  }

   /*
    * Data nodes

    */

   augment "/nw:networks/nw:network/nw:node/nt:termination-point/"
           + "tet:te" {
     description
       "Augmentation to add possibility to reference an element
        in the list of interfaces as defined by RFC 8343.";
     uses tp-to-interface-ref;
   }
 }
]]></sourcecode>
      </section>
    </section>
    <section anchor="security-considerations">
      <name>Security Considerations</name>
      <t>The YANG modules specified in this document define schemas for data
   that is designed to be accessed via network management protocols such
   as NETCONF <xref target="RFC6241"/> or RESTCONF <xref target="RFC8040"/>.  The lowest NETCONF layer
   is the secure transport layer, and the mandatory-to-implement secure
   transport is Secure Shell (SSH) <xref target="RFC6242"/>.  The lowest RESTCONF layer
   is HTTPS, and the mandatory-to-implement secure transport is TLS
   <xref target="RFC8446"/>.</t>
      <t>The NETCONF access control model <xref target="RFC8341"/> provides the means to
   restrict access for particular NETCONF or RESTCONF users to a
   preconfigured subset of all available NETCONF or RESTCONF protocol
   operations and content.</t>
      <t>The YANG module specified in this document imports and augments the
   ietf-network and ietf-network-topology models defined in <xref target="RFC8345"/>.
   The security considerations from <xref target="RFC8345"/> are applicable to the
   module in this document.</t>
      <t>There is a data node defined in this YANG module that is
   writable/creatable/deletable (i.e., config true, which is the
   default).  This data node may be considered sensitive or vulnerable
   in some network environments.  Write operations (e.g., edit-config)
   to this data node without proper protection can have a negative
   effect on network operations.  This is the subtrees and data node
   and its sensitivity/vulnerability:</t>
      <ul spacing="normal">
        <li>tp-to-interface-path: A malicious client could set an arbitrary
path that could allow a client to retrieve incorrect information.
Troubleshooting would be difficult because the bad path would not
be detectable until the client tries to use the leaf to identify
to radio link terminal.</li>
      </ul>
    </section>
    <section anchor="iana-considerations">
      <name>IANA Considerations</name>
      <t>IANA is asked to assign a new URI from the "IETF XML Registry" <xref target="RFC3688"/> as follows:</t>
      <artwork><![CDATA[
URI: urn:ietf:params:xml:ns:yang:ietf-tp-interface-reference-topology
Registrant Contact: The IESG
XML: N/A; the requested URI is an XML namespace.
]]></artwork>
      <t>It is proposed that IANA should record YANG module names in the "YANG
   Module Names" registry <xref target="RFC6020"/> as follows:</t>
      <artwork><![CDATA[
    Name: ietf-tp-interface-reference-topology
    Maintained by IANA?: N
    Namespace:
      urn:ietf:params:xml:ns:yang:ietf-interface-reference-topology
    Prefix: ifref
    Reference: RFC XXXX
]]></artwork>
    </section>
  </middle>
  <back>
    <references>
      <name>References</name>
      <references>
        <name>Normative References</name>
        <reference anchor="RFC8343">
          <front>
            <title>A YANG Data Model for Interface Management</title>
            <author fullname="M. Bjorklund" initials="M." surname="Bjorklund">
              <organization/>
            </author>
            <date month="March" year="2018"/>
            <abstract>
              <t>This document defines a YANG data model for the management of network interfaces.  It is expected that interface-type-specific data models augment the generic interfaces data model defined in this document. The data model includes definitions for configuration and system state (status information and counters for the collection of statistics).</t>
              <t>The YANG data model in this document conforms to the Network Management Datastore Architecture (NMDA) defined in RFC 8342.</t>
              <t>This document obsoletes RFC 7223.</t>
            </abstract>
          </front>
          <seriesInfo name="RFC" value="8343"/>
          <seriesInfo name="DOI" value="10.17487/RFC8343"/>
        </reference>
        <reference anchor="RFC8795">
          <front>
            <title>YANG Data Model for Traffic Engineering (TE) Topologies</title>
            <author fullname="X. Liu" initials="X." surname="Liu">
              <organization/>
            </author>
            <author fullname="I. Bryskin" initials="I." surname="Bryskin">
              <organization/>
            </author>
            <author fullname="V. Beeram" initials="V." surname="Beeram">
              <organization/>
            </author>
            <author fullname="T. Saad" initials="T." surname="Saad">
              <organization/>
            </author>
            <author fullname="H. Shah" initials="H." surname="Shah">
              <organization/>
            </author>
            <author fullname="O. Gonzalez de Dios" initials="O." surname="Gonzalez de Dios">
              <organization/>
            </author>
            <date month="August" year="2020"/>
            <abstract>
              <t>This document defines a YANG data model for representing, retrieving, and manipulating Traffic Engineering (TE) Topologies. The model serves as a base model that other technology-specific TE topology models can augment.</t>
            </abstract>
          </front>
          <seriesInfo name="RFC" value="8795"/>
          <seriesInfo name="DOI" value="10.17487/RFC8795"/>
        </reference>
        <reference anchor="RFC8345">
          <front>
            <title>A YANG Data Model for Network Topologies</title>
            <author fullname="A. Clemm" initials="A." surname="Clemm">
              <organization/>
            </author>
            <author fullname="J. Medved" initials="J." surname="Medved">
              <organization/>
            </author>
            <author fullname="R. Varga" initials="R." surname="Varga">
              <organization/>
            </author>
            <author fullname="N. Bahadur" initials="N." surname="Bahadur">
              <organization/>
            </author>
            <author fullname="H. Ananthakrishnan" initials="H." surname="Ananthakrishnan">
              <organization/>
            </author>
            <author fullname="X. Liu" initials="X." surname="Liu">
              <organization/>
            </author>
            <date month="March" year="2018"/>
            <abstract>
              <t>This document defines an abstract (generic, or base) YANG data model for network/service topologies and inventories.  The data model serves as a base model that is augmented with technology-specific details in other, more specific topology and inventory data models.</t>
            </abstract>
          </front>
          <seriesInfo name="RFC" value="8345"/>
          <seriesInfo name="DOI" value="10.17487/RFC8345"/>
        </reference>
        <reference anchor="RFC2119">
          <front>
            <title>Key words for use in RFCs to Indicate Requirement Levels</title>
            <author fullname="S. Bradner" initials="S." surname="Bradner">
              <organization/>
            </author>
            <date month="March" year="1997"/>
            <abstract>
              <t>In many standards track documents several words are used to signify the requirements in the specification.  These words are often capitalized. This document defines these words as they should be interpreted in IETF documents.  This document specifies an Internet Best Current Practices for the Internet Community, and requests discussion and suggestions for improvements.</t>
            </abstract>
          </front>
          <seriesInfo name="BCP" value="14"/>
          <seriesInfo name="RFC" value="2119"/>
          <seriesInfo name="DOI" value="10.17487/RFC2119"/>
        </reference>
        <reference anchor="RFC8174">
          <front>
            <title>Ambiguity of Uppercase vs Lowercase in RFC 2119 Key Words</title>
            <author fullname="B. Leiba" initials="B." surname="Leiba">
              <organization/>
            </author>
            <date month="May" year="2017"/>
            <abstract>
              <t>RFC 2119 specifies common key words that may be used in protocol  specifications.  This document aims to reduce the ambiguity by clarifying that only UPPERCASE usage of the key words have the  defined special meanings.</t>
            </abstract>
          </front>
          <seriesInfo name="BCP" value="14"/>
          <seriesInfo name="RFC" value="8174"/>
          <seriesInfo name="DOI" value="10.17487/RFC8174"/>
        </reference>
        <reference anchor="RFC6241">
          <front>
            <title>Network Configuration Protocol (NETCONF)</title>
            <author fullname="R. Enns" initials="R." role="editor" surname="Enns">
              <organization/>
            </author>
            <author fullname="M. Bjorklund" initials="M." role="editor" surname="Bjorklund">
              <organization/>
            </author>
            <author fullname="J. Schoenwaelder" initials="J." role="editor" surname="Schoenwaelder">
              <organization/>
            </author>
            <author fullname="A. Bierman" initials="A." role="editor" surname="Bierman">
              <organization/>
            </author>
            <date month="June" year="2011"/>
            <abstract>
              <t>The Network Configuration Protocol (NETCONF) defined in this document provides mechanisms to install, manipulate, and delete the configuration of network devices.  It uses an Extensible Markup Language (XML)-based data encoding for the configuration data as well as the protocol messages.  The NETCONF protocol operations are realized as remote procedure calls (RPCs).  This document obsoletes RFC 4741.  [STANDARDS-TRACK]</t>
            </abstract>
          </front>
          <seriesInfo name="RFC" value="6241"/>
          <seriesInfo name="DOI" value="10.17487/RFC6241"/>
        </reference>
        <reference anchor="RFC8040">
          <front>
            <title>RESTCONF Protocol</title>
            <author fullname="A. Bierman" initials="A." surname="Bierman">
              <organization/>
            </author>
            <author fullname="M. Bjorklund" initials="M." surname="Bjorklund">
              <organization/>
            </author>
            <author fullname="K. Watsen" initials="K." surname="Watsen">
              <organization/>
            </author>
            <date month="January" year="2017"/>
            <abstract>
              <t>This document describes an HTTP-based protocol that provides a programmatic interface for accessing data defined in YANG, using the datastore concepts defined in the Network Configuration Protocol (NETCONF).</t>
            </abstract>
          </front>
          <seriesInfo name="RFC" value="8040"/>
          <seriesInfo name="DOI" value="10.17487/RFC8040"/>
        </reference>
        <reference anchor="RFC6242">
          <front>
            <title>Using the NETCONF Protocol over Secure Shell (SSH)</title>
            <author fullname="M. Wasserman" initials="M." surname="Wasserman">
              <organization/>
            </author>
            <date month="June" year="2011"/>
            <abstract>
              <t>This document describes a method for invoking and running the Network Configuration Protocol (NETCONF) within a Secure Shell (SSH) session as an SSH subsystem.  This document obsoletes RFC 4742.  [STANDARDS-TRACK]</t>
            </abstract>
          </front>
          <seriesInfo name="RFC" value="6242"/>
          <seriesInfo name="DOI" value="10.17487/RFC6242"/>
        </reference>
        <reference anchor="RFC8446">
          <front>
            <title>The Transport Layer Security (TLS) Protocol Version 1.3</title>
            <author fullname="E. Rescorla" initials="E." surname="Rescorla">
              <organization/>
            </author>
            <date month="August" year="2018"/>
            <abstract>
              <t>This document specifies version 1.3 of the Transport Layer Security (TLS) protocol.  TLS allows client/server applications to communicate over the Internet in a way that is designed to prevent eavesdropping, tampering, and message forgery.</t>
              <t>This document updates RFCs 5705 and 6066, and obsoletes RFCs 5077, 5246, and 6961.  This document also specifies new requirements for TLS 1.2 implementations.</t>
            </abstract>
          </front>
          <seriesInfo name="RFC" value="8446"/>
          <seriesInfo name="DOI" value="10.17487/RFC8446"/>
        </reference>
        <reference anchor="RFC8341">
          <front>
            <title>Network Configuration Access Control Model</title>
            <author fullname="A. Bierman" initials="A." surname="Bierman">
              <organization/>
            </author>
            <author fullname="M. Bjorklund" initials="M." surname="Bjorklund">
              <organization/>
            </author>
            <date month="March" year="2018"/>
            <abstract>
              <t>The standardization of network configuration interfaces for use with the Network Configuration Protocol (NETCONF) or the RESTCONF protocol requires a structured and secure operating environment that promotes human usability and multi-vendor interoperability.  There is a need for standard mechanisms to restrict NETCONF or RESTCONF protocol access for particular users to a preconfigured subset of all available NETCONF or RESTCONF protocol operations and content.  This document defines such an access control model.</t>
              <t>This document obsoletes RFC 6536.</t>
            </abstract>
          </front>
          <seriesInfo name="STD" value="91"/>
          <seriesInfo name="RFC" value="8341"/>
          <seriesInfo name="DOI" value="10.17487/RFC8341"/>
        </reference>
        <reference anchor="RFC3688">
          <front>
            <title>The IETF XML Registry</title>
            <author fullname="M. Mealling" initials="M." surname="Mealling">
              <organization/>
            </author>
            <date month="January" year="2004"/>
            <abstract>
              <t>This document describes an IANA maintained registry for IETF standards which use Extensible Markup Language (XML) related items such as Namespaces, Document Type Declarations (DTDs), Schemas, and Resource Description Framework (RDF) Schemas.</t>
            </abstract>
          </front>
          <seriesInfo name="BCP" value="81"/>
          <seriesInfo name="RFC" value="3688"/>
          <seriesInfo name="DOI" value="10.17487/RFC3688"/>
        </reference>
        <reference anchor="RFC6020">
          <front>
            <title>YANG - A Data Modeling Language for the Network Configuration Protocol (NETCONF)</title>
            <author fullname="M. Bjorklund" initials="M." role="editor" surname="Bjorklund">
              <organization/>
            </author>
            <date month="October" year="2010"/>
            <abstract>
              <t>YANG is a data modeling language used to model configuration and state data manipulated by the Network Configuration Protocol (NETCONF), NETCONF remote procedure calls, and NETCONF notifications. [STANDARDS-TRACK]</t>
            </abstract>
          </front>
          <seriesInfo name="RFC" value="6020"/>
          <seriesInfo name="DOI" value="10.17487/RFC6020"/>
        </reference>
      </references>
      <references>
        <name>Informative References</name>
        <reference anchor="RFC8453">
          <front>
            <title>Framework for Abstraction and Control of TE Networks (ACTN)</title>
            <author fullname="D. Ceccarelli" initials="D." role="editor" surname="Ceccarelli">
              <organization/>
            </author>
            <author fullname="Y. Lee" initials="Y." role="editor" surname="Lee">
              <organization/>
            </author>
            <date month="August" year="2018"/>
            <abstract>
              <t>Traffic Engineered (TE) networks have a variety of mechanisms to facilitate the separation of the data plane and control plane.  They also have a range of management and provisioning protocols to configure and activate network resources.  These mechanisms represent key technologies for enabling flexible and dynamic networking.  The term "Traffic Engineered network" refers to a network that uses any connection-oriented technology under the control of a distributed or centralized control plane to support dynamic provisioning of end-to- end connectivity.</t>
              <t>Abstraction of network resources is a technique that can be applied to a single network domain or across multiple domains to create a single virtualized network that is under the control of a network operator or the customer of the operator that actually owns the network resources.</t>
              <t>This document provides a framework for Abstraction and Control of TE Networks (ACTN) to support virtual network services and connectivity services.</t>
            </abstract>
          </front>
          <seriesInfo name="RFC" value="8453"/>
          <seriesInfo name="DOI" value="10.17487/RFC8453"/>
        </reference>
        <reference anchor="RFC8340">
          <front>
            <title>YANG Tree Diagrams</title>
            <author fullname="M. Bjorklund" initials="M." surname="Bjorklund">
              <organization/>
            </author>
            <author fullname="L. Berger" initials="L." role="editor" surname="Berger">
              <organization/>
            </author>
            <date month="March" year="2018"/>
            <abstract>
              <t>This document captures the current syntax used in YANG module tree diagrams.  The purpose of this document is to provide a single location for this definition.  This syntax may be updated from time to time based on the evolution of the YANG language.</t>
            </abstract>
          </front>
          <seriesInfo name="BCP" value="215"/>
          <seriesInfo name="RFC" value="8340"/>
          <seriesInfo name="DOI" value="10.17487/RFC8340"/>
        </reference>
      </references>
    </references>
    <section anchor="examples">
      <name>Examples of the Interface Reference Topology Model</name>
      <t>This appendix provides some examples and illustrations of how the
   Interface Reference Topology Model can be used.  There is one
   extended tree to illustrate the Model and a JSON based instantiation
   of the Interface Reference Model for a small network example.</t>
      <section anchor="a-tree-for-a-complete-interface-reference-topology-model">
        <name>A tree for a complete Interface Reference Topology Model</name>
        <t>The tree below shows the leafs for extending a Network Topology Model
   defined in <xref target="RFC8345"/>, Traffic Engineering (TE) Topologies model
   defined in <xref target="RFC8795"/> with a possibility to reference interface
   management information.</t>
        <sourcecode type="yangtree" name="full-if.tree"><![CDATA[
module: ietf-network
  +--rw networks
     +--rw network* [network-id]
        +--rw network-id                network-id
        +--rw node* [node-id]
           +--rw node-id               node-id
           +--rw nt:termination-point* [tp-id]
              +--rw nt:tp-id           tp-id
              +--rw tet:te!
                 +--rw ifref:tp-to-interface-path?\
                   -> /if:interfaces/interface/name
]]></sourcecode>
      </section>
      <section anchor="a-json-example">
        <name>A JSON example</name>
        <sourcecode type="json" name="exampleInterfRef.json" markers="false"><![CDATA[
{
  "ietf-interfaces:interfaces": {
    "interface": [
      {
        "name": "L2Interface1",
        "description": "'Ethernet Interface 1'",
        "type": "iana-if-type:ethernetCsmacd"
      },
      {
        "name": "L2Interface2",
        "description": "'Ethernet Interface 2'",
        "type": "iana-if-type:ethernetCsmacd"
      }
    ]
  },
  "ietf-network:networks": {
    "network": [
      {
        "network-id": "L2-network",
        "network-types": {
          "ietf-te-topology:te-topology": {
            "ietf-eth-te-topology:eth-tran-topology": {}
          }
        },
        "node": [
          {
            "node-id": "L2-N1",
            "ietf-network-topology:termination-point": [
              {
                "tp-id": "L2-N1-TP1",
                "ietf-te-topology:te-tp-id": "10.10.10.1",
                "ietf-te-topology:te": {
  "ietf-tp-interface-reference-topology:tp-to-interface-path":
     "L2Interface1"
                }
              }
            ]
          },
          {
            "node-id": "L2-N2",
            "ietf-network-topology:termination-point": [
              {
                "tp-id": "L2-N2-TP2",
                "ietf-te-topology:te-tp-id": "10.10.10.2",
                "ietf-te-topology:te": {
  "ietf-tp-interface-reference-topology:tp-to-interface-path":
     "L2Interface2"
                }
              }
            ]
          }
        ],
        "ietf-network-topology:link": [
          {
            "link-id": "L2-N1-N2",
            "source": {
              "source-node": "L2-N1",
              "source-tp": "L2-N1-TP1"
            },
            "destination": {
              "dest-node": "L2-N2",
              "dest-tp": "L2-N2-TP2"
            }
          }
        ]
      }
    ]
  }
}
]]></sourcecode>
      </section>
    </section>
  </back>
  <!-- ##markdown-source:
H4sIAAAAAAAAA81abVPbRh5/r0+xdV4EWiwDoU/qtQkFktABwsXuNJ1e52Yt
r+0tslanXUF8Ge6z3++/D5Jsy4S205tjmEFa7f6fn5d+vx8ZaTKRsN4x+/n4
6hU75YazSzURGZuqkp3nRpRTngr2VkxFKXI8jVShMjVb9iI+HpfiFocf2ubg
WpC9aKLSnC+Ab1LyqelLYab9NOWLoi+n/VJM+wan+kuez/oZN0KbKMWfmSqX
CdNmEsmiTJgpK20O9/e/3j+MeCl4wt6qysh8Ft2p8mZWqqpImIUa3Ygl1iaJ
YyQXpn9KiCNteD75J89UDlqWQkeFTNgvRqV7TKvSgBKNp+WCHn6NUpVrketK
W9wiinhl5qpMItaPGGMyx4cfYnY8z8ainNGSY/IHlXPdXlbljOfy39xIlSfs
rJSp1iqnL2LBZZaw3+hEzN2JF8JviFO1aOMaxuyS53oqRTZpsA1TZczqh4/i
03QmXoQzWzFexuxn0aC6lLl/X8XwuuJ3QrKRSOc5KV9Csg0yvljGS7GQ+Yu5
3beO5Dxm31daNmjODTRUr/0eVJJOxmOc3ILrXcwuWpjeSf+6iuTq7IRd8LEq
uVElMLCzqlSFaCF6L+NMvshFmvFxLKo2itOYDQuY51SmqsF0CvAi46uf1rCq
G8lZn52PWogm7lysw7kXOW2zfEW5Khc4fCuSKJL5tPXW7/cZH2tT8tREo7nU
DC5YLURu2ERMZQ6euPPQCXn+wnq+Uawo1a2cCHwsa4+elmqBBTgSdGhpZYWS
gARrwHLw9xqGrKMCDIzPhMVakwcjc+Qt5GSSwamekJOWalKl9DH6v6OWwR5p
lyXRUnLHl3SywWnmon3EoVqnl+JqJ7IPHz55+/Lkq2dHz+7vAYoblqoqm7Cx
YJUW08od5RnIXRYgQE03udMgcwQqHCpezQiyZr2u4D5CKIQlsbN8BtHC9fMZ
2xmd7YbQDYPveblPiBVP35dff35/v8fu5jKdM6hozDW+g4AtOeRKGIrLH4H6
7AhQY9K6aEmnEa1jCOjE+0KkBmcheScZkpC5E4KEfU2WoCEOYiZgPlGktSwT
Jdu5vjrZZQj+2HtZZUayUwUHy9lQlLcSeE4U8gWJVJU7l6dDbP7w4TkRePQ5
1ALpnsqppckQapaCeQ0y/1XJEvaXwjA0UTapd3FjSjmuDFlMbjkGAlCSK+OM
B84pUwN58jbIlOfEnq6KAglJTPas4lvA6i9svPSG12FTtdjupJljG57c0oJP
Ar1ynHl3ITCrngGNPHmCKEtm5paJiVNSnySr01ZhUwhX3ZHIeVqqfLkAr6XX
DRg2bU9GUIIOPqaoKCLhf1RFjrpSCDZEZk5NVYromGm5KDKJjDZhs5IXMFSe
QdCInEjjxnkLOQ8ob/klaAwEp3NeQJjsWXzgNrboDw4muCXdw0GtMFaZdtwC
DQyAAzcEQUfb1v7cWfu+tfYnKJis6Tg3vUDhU0F1VqioXRgVL/Deyx+Ho96e
+8uu3tjnt2d///H87dkpPQ9fH19c1A9hx/D1mx8vTpun5uTJm8vLs6tTdxir
bG3p8vhn/CFN995cj87fXB1f9DYUaVXsnNCaHsRL1siJX53CTB3H359cs4Mj
7+aHBwdfI7h5nz/48ggvd3ORO2Qqz5b+FUKEqRWF4KWNorD9lBeU1lGYAYWe
q7uczeFiVoqjVhy8tlEehHVVpWsBytqPXSMjiv6DH0bVp6E3mEVFtbGtUg1K
1ACvX4elfvAWqgltrGWD/C7JnT3r1rN9BMoBPKAVtfs2ag+MoFUUlOyzfr+8
Y8BmVAthwc38OYqB/ndsIKdJ/UEP6scB1ReWg+gDaq3SYu3T4rc9OY2Jo959
y5t/r7AgikY+XjaPEg37ALZsSX8rSvJ41juID3rfhJpIFziHl15V5gkBTApO
npO8X2QJCik6mjwGEUASTNjhVL5nYBoPfg0BAbHSkesVYslqbc/vHEmslXR6
sFJGqSlhj85tFsj9NqyrUmmjN38peiO2YobtbUONVJ90Iu4oHRyE1s96KbGF
ssaW1wiT03WqAoogl2dtmO0a2m3shaZvpcIZcX3DXqoSTO6cn41e7rKTk+PL
a/bTKwcNzZ6hYtmB+OkVGgNtEvY3KsONSmxf+YIoj4HxuygaDH6xfd7xr+yn
uULEppItkzchNiqbEbCiDSULMZHIW3pAaGwqx8tzz9iZ/dbRN7Z+Ah3bO8Xv
1qB19IUd8B7qBNchNu1fB6CuLm8dwGpj1wHEboi/X+3f1qHUTVsHgHcyvmj1
ZetHN7uwLXAeaLs8TB9hBgP0bcYqnawzIELVkVFQfYcfV4PBtiqUI7QprxbQ
HqU+DwF1gLoVLs2iPkRuw7rLpkXLrm1nJKkD8WGYXNIWGbYEe7AJ8ny2W6FW
zQfquTNVkYUOqCkstT/MV0qa4IxxkOGJKpalnM0N20l32eH+4T4jR0PQqACY
Ej05RIFkgPqRoW/LjSvWeI3Azld0KK5SxB2UXccoAixcKrg1ikExif2Bt3Ar
7fyJEgzhoFIa1GlVkavTyhgiKJckrAWKCKsMVJAOAL2pytbLoCW1otojGRck
OkOFTVGVuuI2W7pyRVfj39CK4N0DcX6eihyoSeTaBRMvKFvUsGFTm34/PIUB
u+1a+IhD5IEwW+7aRpgdxWkQRCPGpygWxQx2VNfRuhZFxmkYZpM67T/19VrY
sDM3pkgGAztGEyIOsWzgSe9TB7sbJGttLSTuUAvblBBKAMgI1QZ9I0sgQ28j
0oRJoTRu8MzNIhuU05S27n4D1l3jTKel0SKbkgyCNCooPbOcwiFAoI69w5XC
8U0GdtA/2O/DzHwC2fSYl7KE6ZWqms3d6DHuSHntbDL41H7+lL2icSLE6aT3
6YD+zPzaRpkGYKBhCxEgIwBzjQZ5bYO+6WE3RxY+QjjfaDlkzUWG4NRZNAaR
MDszsPsckXWks7uerleVrTd6oTrt6Tfh0H146OARXF54JOjUS2ovwUZg08Wn
doDZawWAVgxGTwtbsPXh3moM2hZ9giiIuDUd2uKFim8dBS1GNsq4ir33h0r2
XjtjfGbLKOzqbbVBCObYIXSapVA7QVRR1IDLTJq1WRL07EVUI5KrpUS3TCC5
DZlUNFHoMFZv8PgNfYMLlxRw+wte3sDvv+3RzLvX/uKbikeU5DEV77btoHBW
lcQlmnwNnZfczQ8i5hrqVkxBe1eI1AXJja7T8cl0OhcLsG1TH/RLYOzMzPbb
Ws7yekTkphx4vZUwA18yt2YkRamMSql711U6t5ah2dXZ6OTN1Uvfqn5xeHSA
VhW43p4N2x++2redvGMhU3cCqglHM74UNo6BJDsjIAkg1pUosmz9azfs1RkR
JE1oqLG0ekKacOS5Y5a/+iQgDh204VwgQu4Mh693G1oP10mqqW7T9Ho0uh4+
Ev0q7tHFkGB4ERwdfWGHGV6RgX0/DEvdTMcPWeppH4nTj22ddGigon0urYdi
HgYpmZKMTKuMlzWGtjpg4qWdvHHfAwLvVM5Auk3UyK/kMnaGdovSjtPMqwtO
MAbbUhTBSq2QiBMaAHWZ7EMW67odB6OeyIJlq4Z2R2rng53NohWe3j429QTp
4GPpio+5MrB9ws5ueIFKJLWSgNw8QSGrrzFRM10KV3lOQkxtE7VRHHiPpLN3
IIxwDVJU0u4JPAn7xHZkLOI95nRmL9laA2ZPGfDwKjO7sS9KGgoWfEl+Hpgm
jaOQkXQFQrq9rbIcogAedzeDULYQdSAQ+a0sVW61AtA/gUzR1vyOiGcgjfq2
vqNv1/qi8gKqqQglZEFXRKU1JF/B0Sx3zm/pfiJHKUN02Zud6ZTKR2wItDRo
A5MhdFRjGuA4G6pR2lBFNgN7ChxD+4PAsM0qidVcn3WWBzRYWHBYgVQVXDWT
ZK/u1oE8BnTzcizh++UyNA7czpHrywlOk18w5s/aFAbfFbdkQ6kqS2Jx5dLH
wRmhFIJG9FwpW63ehasOmpyTnxu8pJyqeBLAmE8carcPtaCHQycECdraUYVK
InM9g6fHXtuBqgDIVUoqVB2BLaKbT6RCcs1vQgVmp9/s/PjquCtp2XXyBX3j
Ug3XlHasku/Yj2/Pm5l6zxbi7y4vUJ3PqFFZ9rw7Pvviq6/IHbWfoWuoy+Zi
nE/Yn52IRR4ddS0nbq6R2EBxfjZ8FYGehF0Njr+xNNIdBsIuWCHSia/cUlyP
6GJHmGXdZgEydEV51ZqDFQfUSeqh6FtOViKBBRMqGHsdRYDcXJFd0ccejjnh
hESGzrFTNqSwK3ub+igh0PZLdGG+E0OBRLQ+B+81JMtg4m3ho1L/KLZrO8EC
eVQH25V6qJo0XZITJ12Bjnl6Q6Z29p5T3q0b3wf/r8JN4z48Ef7QvQ/RpLqi
EPlEvm8yrA15YacLGllWkWm4KAeEc/ixD7WPwOvvp6iRiVuJQeUutL1HppyQ
adDdDLlbwOa80MFw13A/DN9c+UtEmdM/ZhhZTyoekEMzjORMLyix1xHdsemu
ro4dCW5fquiDeYxg6yRvj48FRTm6dNB1FHFliePU9TVr49gAyeWursS995g7
WJf8u6HYu1g/V9reStT2ahP8trv4By4/vGSjcD0RmiXnMCtrn7JfQvUiJ7/W
rcvKHnxhaz/Nl/UjYJ5gUt/RBriyYROgX+3Y3tHLAT7FkFXoKyeKVQz2vXOz
6wI/2RiG+882ICSdtzv/2Dzzh+97aGrSX730OXZ+5n3DKfs3+mcg6ld7a5P4
FsJe4jvaXr2GpV88sc0coUeY8aV3cVg710Fvr/neaohp29Mz+JEdzje+ePC0
fYAGFrRTwmDp38PoPRH+1AlcPp2EHvx+71H0HP5Oeg7/MD32L5mTpazXdqJ6
0tBI1q9skWvtGY6bAKdNWt0v0P+F1HD9x/X7n6T1vLY37AZXKyfsO6qIlXP3
rYPN832bLDhhi6lVxuodDWdXbYNpqFnvhjYdeA3JJiKnwKKNqj+6Xke3XVzh
5MF+7H8fedQL+FHDks640PNVyapfbeC+jx56bwe2+71Hq+Pwf6eOQ6hjHd02
mXao47FH/xJ1HP4pddTPv7Y8p1vQ1Js87E+0Y8XIN3Xo5ngbjl9/6Xuv7XTI
ZpcpVj1pZdv9Gk7EWuMtpAsxfV5Bu6lOt6dB6uxlFWm3VDdDcnS/JW365OgU
i8IwpgSJ/LllLjrlme4ajG4D818zf/cnby0AAA==

-->

</rfc>
